cyclicmodel/__init__.py
cyclicmodel/define_model.py
cyclicmodel-0.0.4.dist-info/METADATA
cyclicmodel-0.0.4.dist-info/RECORD
cyclicmodel-0.0.4.dist-info/WHEEL
cyclicmodel-0.0.4.dist-info/top_level.txt
tests/__init__.py
tests/context.py
tests/test_define_model.py
