Metadata-Version: 2.1
Name: cyclicmodel
Version: 0.0.4
Summary: statistical causality discovery based on cyclic model
Home-page: https://github.com/inoueakimitsu/cyclicmodel
Author: Akimitsu INOUE
Author-email: akimitsu.inoue@gmail.com
License: UNKNOWN
Platform: UNKNOWN
Classifier: Development Status :: 2 - Pre-Alpha
Classifier: Intended Audience :: Science/Research
Classifier: License :: OSI Approved :: MIT License
Classifier: Operating System :: OS Independent
Classifier: Programming Language :: Python :: 3.5
Classifier: Topic :: Scientific/Engineering :: Mathematics
Requires-Dist: theano
Requires-Dist: numpy
Requires-Dist: pymc3
